JMaster.py
README.md
README.rst
setup.py
JMaster.egg-info/PKG-INFO
JMaster.egg-info/SOURCES.txt
JMaster.egg-info/dependency_links.txt
JMaster.egg-info/entry_points.txt
JMaster.egg-info/requires.txt
JMaster.egg-info/top_level.txt
img/contest.png
img/parse-contest.png
img/parse-gym.png
img/test-problem.png