Metadata-Version: 1.1
Name: JMaster
Version: 1.0.3
Summary: JMaster, contest parser and tester for CodeForces
Home-page: https://github.com/palayutm/JMaster
Author: palayutm
Author-email: palayutm@gmail.com
License: GPL
Platform: UNKNOWN
Classifier: Development Status :: 4 - Beta
Classifier: License :: OSI Approved :: GNU General Public License (GPL)
Classifier: Environment :: Console
Classifier: Intended Audience :: End Users/Desktop
Classifier: Natural Language :: English
Classifier: Operating System :: POSIX :: Linux
Classifier: Operating System :: MacOS :: MacOS X
Classifier: Operating System :: POSIX :: SunOS/Solaris
Classifier: Programming Language :: Python :: 3.3
Classifier: Programming Language :: Python :: 3.4
Classifier: Programming Language :: Python :: 3.5
Classifier: Programming Language :: Python :: 3.6
Classifier: Topic :: Utilities
